renoir/__init__.py
renoir/analyzer.py
renoir/color/__init__.py
renoir/color/analysis.py
renoir/color/extraction.py
renoir/color/visualization.py
renoir_wikiart-3.0.2.dist-info/licenses/LICENSE
renoir_wikiart-3.0.2.dist-info/METADATA
renoir_wikiart-3.0.2.dist-info/WHEEL
renoir_wikiart-3.0.2.dist-info/top_level.txt
renoir_wikiart-3.0.2.dist-info/RECORD
