Metadata-Version: 2.4
Name: renoir-wikiart
Version: 3.0.2
Summary: A pedagogical tool for analyzing artist-specific works from WikiArt with computational color theory capabilities
Home-page: https://github.com/MichailSemoglou/renoir
Author: Michail Semoglou
Author-email: Michail Semoglou <m.semoglou@tongji.edu.cn>
License: MIT
Project-URL: Homepage, https://github.com/MichailSemoglou/renoir
Project-URL: Documentation, https://github.com/MichailSemoglou/renoir#readme
Project-URL: Repository, https://github.com/MichailSemoglou/renoir
Project-URL: Bug Tracker, https://github.com/MichailSemoglou/renoir/issues
Keywords: art-history,dataset-analysis,digital-humanities,education,computational-design,color-theory
Classifier: Development Status :: 4 - Beta
Classifier: Intended Audience :: Education
Classifier: Intended Audience :: Science/Research
Classifier: Programming Language :: Python :: 3
Classifier: Programming Language :: Python :: 3.8
Classifier: Programming Language :: Python :: 3.9
Classifier: Programming Language :: Python :: 3.10
Classifier: Programming Language :: Python :: 3.11
Classifier: Programming Language :: Python :: 3.12
Classifier: Topic :: Education
Classifier: Topic :: Scientific/Engineering :: Information Analysis
Classifier: Topic :: Artistic Software
Requires-Python: >=3.8
License-File: LICENSE
Requires-Dist: datasets>=2.0.0
Requires-Dist: Pillow>=8.0.0
Requires-Dist: numpy>=1.20.0
Requires-Dist: scikit-learn>=1.0.0
Requires-Dist: pandas>=1.3.0
Provides-Extra: dev
Requires-Dist: pytest>=7.0; extra == "dev"
Requires-Dist: black>=22.0; extra == "dev"
Requires-Dist: flake8>=4.0; extra == "dev"
Requires-Dist: jupyter>=1.0.0; extra == "dev"
Provides-Extra: visualization
Requires-Dist: matplotlib>=3.5.0; extra == "visualization"
Requires-Dist: seaborn>=0.11.0; extra == "visualization"
Dynamic: license-file
Dynamic: requires-python
